{"is_source_file": false, "format": "XML", "description": "This file defines a menu resource for an Android application, specifying menu items grouped under a selectable group and individual navigation items.", "external_files": [], "external_methods": [], "published": [], "classes": [], "methods": [], "calls": [], "search-terms": ["drawer_menu", "Android menu resource", "menu XML", "navigation drawer", "app:checkableBehavior"], "state": 2, "file_id": 28, "knowledge_revision": 58, "git_revision": "", "hash": "35384a7cabd4fb79f2c7848cd4c8a60a", "format-version": 4, "code-base-name": "shopping_app_frontend", "filename": "shopping_app_frontend/app/src/main/res/menu/drawer_menu.xml", "revision_history": [{"58": ""}]}